azure/mgmt/redis/__init__.py
azure/mgmt/redis/_configuration.py
azure/mgmt/redis/_patch.py
azure/mgmt/redis/_redis_management_client.py
azure/mgmt/redis/_serialization.py
azure/mgmt/redis/_version.py
azure/mgmt/redis/py.typed
azure/mgmt/redis/aio/__init__.py
azure/mgmt/redis/aio/_configuration.py
azure/mgmt/redis/aio/_patch.py
azure/mgmt/redis/aio/_redis_management_client.py
azure/mgmt/redis/aio/operations/__init__.py
azure/mgmt/redis/aio/operations/_access_policy_assignment_operations.py
azure/mgmt/redis/aio/operations/_access_policy_operations.py
azure/mgmt/redis/aio/operations/_async_operation_status_operations.py
azure/mgmt/redis/aio/operations/_firewall_rules_operations.py
azure/mgmt/redis/aio/operations/_linked_server_operations.py
azure/mgmt/redis/aio/operations/_operations.py
azure/mgmt/redis/aio/operations/_patch.py
azure/mgmt/redis/aio/operations/_patch_schedules_operations.py
azure/mgmt/redis/aio/operations/_private_endpoint_connections_operations.py
azure/mgmt/redis/aio/operations/_private_link_resources_operations.py
azure/mgmt/redis/aio/operations/_redis_operations.py
azure/mgmt/redis/models/__init__.py
azure/mgmt/redis/models/_models_py3.py
azure/mgmt/redis/models/_patch.py
azure/mgmt/redis/models/_redis_management_client_enums.py
azure/mgmt/redis/operations/__init__.py
azure/mgmt/redis/operations/_access_policy_assignment_operations.py
azure/mgmt/redis/operations/_access_policy_operations.py
azure/mgmt/redis/operations/_async_operation_status_operations.py
azure/mgmt/redis/operations/_firewall_rules_operations.py
azure/mgmt/redis/operations/_linked_server_operations.py
azure/mgmt/redis/operations/_operations.py
azure/mgmt/redis/operations/_patch.py
azure/mgmt/redis/operations/_patch_schedules_operations.py
azure/mgmt/redis/operations/_private_endpoint_connections_operations.py
azure/mgmt/redis/operations/_private_link_resources_operations.py
azure/mgmt/redis/operations/_redis_operations.py
azure_mgmt_redis-14.5.0.dist-info/LICENSE
azure_mgmt_redis-14.5.0.dist-info/METADATA
azure_mgmt_redis-14.5.0.dist-info/WHEEL
azure_mgmt_redis-14.5.0.dist-info/top_level.txt
azure_mgmt_redis-14.5.0.dist-info/RECORD
